grobid_client/__init__.py
grobid_client/api/__init__.py
grobid_client/api/pdf/__init__.py
grobid_client/api/pdf/process_fulltext_document.py
grobid_client/client.py
grobid_client/models/__init__.py
grobid_client/models/address.py
grobid_client/models/affiliation.py
grobid_client/models/article.py
grobid_client/models/article_citations.py
grobid_client/models/author.py
grobid_client/models/citation.py
grobid_client/models/citation_ids.py
grobid_client/models/citation_scopes.py
grobid_client/models/citation_titles.py
grobid_client/models/pers_name.py
grobid_client/models/process_form.py
grobid_client/models/ref.py
grobid_client/models/section.py
grobid_client/models/text_with_refs.py
grobid_client/models/uploaded_file.py
grobid_client/py.typed
grobid_client/types.py
grobid_client-0.8.7.dist-info/METADATA
grobid_client-0.8.7.dist-info/WHEEL
grobid_client-0.8.7.dist-info/RECORD
