Metadata-Version: 2.1
Name: grobid-client
Version: 0.8.7
Summary: A client library for accessing Grobid
Requires-Python: >=3.7,<4.0
Classifier: Programming Language :: Python :: 3
Classifier: Programming Language :: Python :: 3.7
Classifier: Programming Language :: Python :: 3.8
Classifier: Programming Language :: Python :: 3.9
Classifier: Programming Language :: Python :: 3.10
Classifier: Programming Language :: Python :: 3.11
Classifier: Programming Language :: Python :: 3.12
Requires-Dist: attrs (>=20.1.0,<22.0.0)
Requires-Dist: beautifulsoup4 (>=4.10.0,<5.0.0)
Requires-Dist: h11 (>=0.12.0)
Requires-Dist: httpx (==0.23.0)
Requires-Dist: lxml (>=4.7.1,<5.0.0)
Requires-Dist: python-dateutil (>=2.8.0,<3.0.0)
